LICENSE
pickledb_ujson.py
pickledb_ujson-1.0.16.dist-info/LICENSE
pickledb_ujson-1.0.16.dist-info/WHEEL
pickledb_ujson-1.0.16.dist-info/METADATA
pickledb_ujson-1.0.16.dist-info/RECORD
