Metadata-Version: 2.1
Name: pickledb-ujson
Version: 1.0.16
Summary: Fork of PickleDB using ujson
Home-page: https://github.com/Divkix/pickledb_ujson
License: BSD-3-Clause License
Keywords: pickledb,pickledb ujson
Author: Harrison Erd
Author-email: erdh@mail.broward.edu
Requires-Python: >=3.7,<4.0
Classifier: Development Status :: 5 - Production/Stable
Classifier: Intended Audience :: Developers
Classifier: License :: OSI Approved :: BSD License
Classifier: License :: Other/Proprietary License
Classifier: Natural Language :: English
Classifier: Operating System :: OS Independent
Classifier: Programming Language :: Python :: 3
Classifier: Programming Language :: Python :: 3.7
Classifier: Programming Language :: Python :: 3.8
Classifier: Programming Language :: Python :: 3.9
Classifier: Programming Language :: Python :: 3.10
Classifier: Programming Language :: Python :: 3.11
Classifier: Programming Language :: Python :: 3
Classifier: Programming Language :: Python :: Implementation :: CPython
Classifier: Topic :: Database
Requires-Dist: ujson (==5.7.0)
Project-URL: Bug Tracker, https://github.com/Divkix/pickledb_ujson/issues
Project-URL: Community, https://t.me/DivideProjects
Project-URL: Documentation, https://patx.github.io/pickledb/commands.html
Project-URL: Repository, https://github.com/Divkix/pickledb_ujson
